squid/__init__.py
squid/constants.py
squid/calcs/__init__.py
squid/calcs/aneb.py
squid/calcs/neb.py
squid/calcs/rate_calc.py
squid/calcs/spline_neb.py
squid/console_scripts/__init__.py
squid/console_scripts/chkDFT.py
squid/console_scripts/procrustes.py
squid/console_scripts/pysub.py
squid/console_scripts/scanDFT.py
squid/files/__init__.py
squid/files/cml_io.py
squid/files/mdl_io.py
squid/files/misc.py
squid/files/xyz_io.py
squid/forcefields/__init__.py
squid/forcefields/connectors.py
squid/forcefields/coulomb.py
squid/forcefields/helper.py
squid/forcefields/lj.py
squid/forcefields/morse.py
squid/forcefields/opls.py
squid/forcefields/parameters.py
squid/forcefields/smrff.py
squid/forcefields/tersoff.py
squid/forcefields/potentials/__init__.py
squid/forcefields/potentials/junk.smrff
squid/forcefields/potentials/oplsaa.prm
squid/forcefields/sinSmooth/__init__.py
squid/forcefields/sinSmooth/coupled.py
squid/forcefields/sinSmooth/inout.py
squid/forcefields/sinSmooth/lr.py
squid/g09/__init__.py
squid/g09/g09.py
squid/g09/utils.py
squid/geometry/__init__.py
squid/geometry/misc.py
squid/geometry/packmol.py
squid/geometry/spatial.py
squid/geometry/transform.py
squid/installers/__init__.py
squid/installers/install_helper.py
squid/installers/install_lammps.py
squid/installers/install_nlopt.py
squid/installers/install_openmpi.py
squid/installers/install_packmol.py
squid/installers/install_squid.py
squid/jdftx/__init__.py
squid/jdftx/jdftx.py
squid/jdftx/jdftx_cards.py
squid/jobs/__init__.py
squid/jobs/container.py
squid/jobs/nbs.py
squid/jobs/queue_manager.py
squid/jobs/slurm.py
squid/jobs/submission.py
squid/lammps/__init__.py
squid/lammps/job.py
squid/lammps/parser.py
squid/lammps/io/__init__.py
squid/lammps/io/data.py
squid/lammps/io/dump.py
squid/lammps/io/thermo.py
squid/maths/__init__.py
squid/maths/lhs.py
squid/optimizers/__init__.py
squid/optimizers/backtrack.py
squid/optimizers/bfgs.py
squid/optimizers/conjugate_gradient.py
squid/optimizers/fire.py
clancyLab_squid-2.1.6.dist-info/METADATA
clancyLab_squid-2.1.6.dist-info/WHEEL
clancyLab_squid-2.1.6.dist-info/entry_points.txt
clancyLab_squid-2.1.6.dist-info/top_level.txt
clancyLab_squid-2.1.6.dist-info/RECORD
