Metadata-Version: 2.1
Name: clancyLab-squid
Version: 2.1.6
Summary: A set of modules to aid in atomistic and molecular simulations.
Home-page: https://github.com/clancylab/squid
Author: Clancy Group
Author-email: ClancyLabJHU@gmail.com
License: UNKNOWN
Platform: UNKNOWN
Classifier: Programming Language :: Python :: 3
Classifier: License :: Other/Proprietary License
Classifier: Operating System :: OS Independent
Requires-Dist: pyDOE
Requires-Dist: numpy
Requires-Dist: scipy
Requires-Dist: psutil
